calplot/__init__.py
calplot/calplot.py
calplot-0.1.7.4.dist-info/AUTHORS.rst
calplot-0.1.7.4.dist-info/LICENSE.rst
calplot-0.1.7.4.dist-info/METADATA
calplot-0.1.7.4.dist-info/WHEEL
calplot-0.1.7.4.dist-info/top_level.txt
calplot-0.1.7.4.dist-info/RECORD
