Metadata-Version: 2.1
Name: calplot
Version: 0.1.7.4
Summary: Calendar heatmaps from Pandas time series data
Home-page: https://github.com/tomkwok/calplot
Author: Tom Kwok
Author-email: tom@tomkwok.com
License: MIT License
Platform: any
Classifier: Intended Audience :: Developers
Classifier: Intended Audience :: Science/Research
Classifier: Operating System :: OS Independent
Classifier: Programming Language :: Python
Classifier: Programming Language :: Python :: 3
Classifier: Programming Language :: Python :: 3.7
Classifier: Programming Language :: Python :: 3.8
Classifier: Programming Language :: Python :: 3.9
Classifier: Topic :: Scientific/Engineering
License-File: LICENSE.rst
License-File: AUTHORS.rst
Requires-Dist: matplotlib
Requires-Dist: numpy
Requires-Dist: pandas (>=1)
